geoequity-1.0.2.dist-info/licenses/LICENSE
models/__init__.py
models/interpolation.py
models/spatial.py
two_stage/__init__.py
two_stage/model.py
two_stage/visualization.py
utils/split.py
geoequity-1.0.2.dist-info/METADATA
geoequity-1.0.2.dist-info/WHEEL
geoequity-1.0.2.dist-info/top_level.txt
geoequity-1.0.2.dist-info/RECORD
