Metadata-Version: 2.4
Name: geoequity
Version: 1.0.2
Summary: Spatial Equity Assessment for Machine Learning Models
Author-email: Zhehao Liang <zliang7@nd.edu>
License: MIT
Project-URL: Homepage, https://github.com/px39n/geoequity
Project-URL: Documentation, https://px39n.github.io/geoequity/
Project-URL: Repository, https://github.com/px39n/geoequity
Project-URL: Issues, https://github.com/px39n/geoequity/issues
Classifier: Development Status :: 3 - Alpha
Classifier: Intended Audience :: Science/Research
Classifier: Operating System :: OS Independent
Classifier: Programming Language :: Python :: 3
Classifier: Programming Language :: Python :: 3.8
Classifier: Programming Language :: Python :: 3.9
Classifier: Programming Language :: Python :: 3.10
Classifier: Programming Language :: Python :: 3.11
Classifier: Topic :: Scientific/Engineering :: GIS
Classifier: Topic :: Scientific/Engineering :: Atmospheric Science
Requires-Python: >=3.8
License-File: LICENSE
Requires-Dist: numpy>=1.20
Requires-Dist: pandas>=1.3
Requires-Dist: scikit-learn>=1.0
Requires-Dist: matplotlib>=3.4
Requires-Dist: tqdm>=4.60
Provides-Extra: full
Requires-Dist: pygam>=0.8.0; extra == "full"
Requires-Dist: xarray>=0.19; extra == "full"
Requires-Dist: geopandas>=0.10; extra == "full"
Provides-Extra: dev
Requires-Dist: pytest>=6.0; extra == "dev"
Requires-Dist: jupyter>=1.0; extra == "dev"
Dynamic: license-file
